setup.py
distributions_06272020/Binomialdistribution.py
distributions_06272020/Gaussiandistribution.py
distributions_06272020/Generaldistribution.py
distributions_06272020/__init__.py
distributions_06272020.egg-info/PKG-INFO
distributions_06272020.egg-info/SOURCES.txt
distributions_06272020.egg-info/dependency_links.txt
distributions_06272020.egg-info/not-zip-safe
distributions_06272020.egg-info/top_level.txt