Metadata-Version: 1.0
Name: distributions-06272020
Version: 0.112
Summary: Gaussian distributions
Home-page: UNKNOWN
Author: UNKNOWN
Author-email: UNKNOWN
License: UNKNOWN
Platform: UNKNOWN
